tdf.extensionuploadcenter-0.44-py2.7-nspkg.pth
tdf/extensionuploadcenter/INTEGRATION.txt
tdf/extensionuploadcenter/__init__.py
tdf/extensionuploadcenter/__init__.pyc
tdf/extensionuploadcenter/adapter.py
tdf/extensionuploadcenter/adapter.pyc
tdf/extensionuploadcenter/configure.zcml
tdf/extensionuploadcenter/customreleasename.py
tdf/extensionuploadcenter/customreleasename.pyc
tdf/extensionuploadcenter/eupcenter.py
tdf/extensionuploadcenter/eupcenter.pyc
tdf/extensionuploadcenter/eupproject.py
tdf/extensionuploadcenter/eupproject.pyc
tdf/extensionuploadcenter/euprelease.py
tdf/extensionuploadcenter/euprelease.pyc
tdf/extensionuploadcenter/eupreleaselink.py
tdf/extensionuploadcenter/eupreleaselink.pyc
tdf/extensionuploadcenter/eupsmallproject.py
tdf/extensionuploadcenter/eupsmallproject.pyc
tdf/extensionuploadcenter/interfaces.py
tdf/extensionuploadcenter/mailtoauthor.py
tdf/extensionuploadcenter/mailtoauthor.pyc
tdf/extensionuploadcenter/notifications.py
tdf/extensionuploadcenter/notifications.pyc
tdf/extensionuploadcenter/permissions.zcml
tdf/extensionuploadcenter/releasecustomurl.py
tdf/extensionuploadcenter/releasecustomurl.pyc
tdf/extensionuploadcenter/setuphandlers.py
tdf/extensionuploadcenter/setuphandlers.pyc
tdf/extensionuploadcenter/tests.py
tdf/extensionuploadcenter/tests.pyc
tdf/extensionuploadcenter/upgrades.py
tdf/extensionuploadcenter/upgrades.pyc
tdf/extensionuploadcenter/upgrades.zcml
tdf/extensionuploadcenter/eupcenter_templates/own_project.pt
tdf/extensionuploadcenter/eupcenter_templates/view.pt
tdf/extensionuploadcenter/eupproject_templates/view.pt
tdf/extensionuploadcenter/euprelease_templates/view.pt
tdf/extensionuploadcenter/eupreleaselink_templates/view.pt
tdf/extensionuploadcenter/eupsmallproject_templates/view.pt
tdf/extensionuploadcenter/locales/README.txt
tdf/extensionuploadcenter/locales/tdf.extensionuploadcenter.pot
tdf/extensionuploadcenter/locales/de/LC_MESSAGES/tdf.extensionuploadcenter.po
tdf.extensionuploadcenter-0.44.dist-info/LICENSE.GPL
tdf.extensionuploadcenter-0.44.dist-info/LICENSE.txt
tdf.extensionuploadcenter-0.44.dist-info/METADATA
tdf.extensionuploadcenter-0.44.dist-info/WHEEL
tdf.extensionuploadcenter-0.44.dist-info/entry_points.txt
tdf.extensionuploadcenter-0.44.dist-info/namespace_packages.txt
tdf.extensionuploadcenter-0.44.dist-info/top_level.txt
tdf.extensionuploadcenter-0.44.dist-info/RECORD
