Metadata-Version: 2.1
Name: tdf.extensionuploadcenter
Version: 0.44
Summary: TDF Extension Upload Center
Home-page: http://github.com/tdf/tdf.extensionuploadcenter
Author: Andreas Mantke
Author-email: maand@gmx.de
License: GPL
Keywords: Plone Add-On LibreOffice extension extensionuploadcenter
Platform: UNKNOWN
Classifier: Framework :: Plone
Classifier: Programming Language :: Python
Classifier: Topic :: Software Development :: Libraries :: Python Modules
Requires-Dist: setuptools
Requires-Dist: plone.app.dexterity
Requires-Dist: plone.namedfile[blobs]
Requires-Dist: collective.dexteritytextindexer
Requires-Dist: cioppino.twothumbs
Requires-Dist: plone.formwidget.recaptcha
